{
    "key": "group_54f751b03a06a",
    "title": "Clients Page Fields",
    "fields": [],
    "location": [
        [
            {
                "param": "page_template",
                "operator": "==",
                "value": "page-templates\/clients_page_template.php"
            }
        ]
    ],
    "menu_order": 10,
    "position": "normal",
    "style": "default",
    "label_placement": "top",
    "instruction_placement": "label",
    "hide_on_screen": [
        "the_content",
        "excerpt",
        "custom_fields",
        "discussion",
        "comments",
        "revisions",
        "slug",
        "author",
        "format",
        "featured_image",
        "categories",
        "tags",
        "send-trackbacks"
    ],
    "active": 1,
    "description": "",
    "modified": 1457373533
}